tictactoe_py-1.0.0.dist-info/DESCRIPTION.rst
tictactoe_py-1.0.0.dist-info/WHEEL
tictactoe_py-1.0.0.dist-info/top_level.txt
tictactoe_py-1.0.0.dist-info/metadata.json
tictactoe_py-1.0.0.dist-info/METADATA
tictactoe_py-1.0.0.dist-info/RECORD
tictactoe/__init__.py
